setup.py
feng/__init__.py
feng.egg-info/PKG-INFO
feng.egg-info/SOURCES.txt
feng.egg-info/dependency_links.txt
feng.egg-info/pbr.json
feng.egg-info/requires.txt
feng.egg-info/top_level.txt
feng/importance/__init__.py
feng/importance/importance.py
feng/pipeline/FeatureUnion.py
feng/pipeline/Pipeline.py
feng/pipeline/__init__.py
feng/preprocessing/DateTimeFeatures.py
feng/preprocessing/__init__.py