Metadata-Version: 1.1
Name: feng
Version: 0.2.0
Summary: Feng is a module for feature engineering.
Home-page: https://github.com/mewwts/feng
Author: Alexander Svanevik, Anders Aagard, Mats Julian Olsen
Author-email: mats@plysjbyen.net
License: UNKNOWN
Platform: UNKNOWN
Classifier: Programming Language :: Python
Classifier: License :: OSI Approved :: MIT License
